opil/__init__.py
opil/custom_eval.py
opil/generate_opil_from_strateos.py
opil/json_ld_writer.py
opil/opil_demo.py
opil/opil_factory.py
opil/shacl_validator.py
opil/rdf/SBO_OWL.rdf
opil/rdf/TimeSeriesProtocol.ttl
opil/rdf/YeastSTATES_1.0_Time_Series_Round_1.ttl
opil/rdf/catalog-v001.xml
opil/rdf/om-2.0.rdf
opil/rdf/opil-shacl.shapes.ttl
opil/rdf/opil.ttl
opil/rdf/sbol3.ttl
opil/rdf/sd2.ttl
opil/sparql/badInstances.sparql
opil/sparql/fileType.sparql
opil/sparql/measurementType.sparql
opil/sparql/media.sparql
opil/sparql/metadata.sparql
opil/sparql/omMeasures.sparql
opil/sparql/parameters.sparql
opil/sparql/replicates.sparql
opil/sparql/sampleSet.sparql
opil/sparql/strains.sparql
opil/sparql/timepoints.sparql
opil/sparql/variableComponents.sparql
opil-1.0a6.dist-info/METADATA
opil-1.0a6.dist-info/WHEEL
opil-1.0a6.dist-info/top_level.txt
opil-1.0a6.dist-info/RECORD
