Metadata-Version: 2.1
Name: opil
Version: 1.0a6
Summary: Python package for demonstrating OPIL
Home-page: UNKNOWN
Author: UNKNOWN
Author-email: UNKNOWN
License: UNKNOWN
Platform: UNKNOWN
Requires-Dist: sbol3 (>=1.0a4)
Requires-Dist: rdflib (>=5.0.0)
Requires-Dist: rdflib-jsonld (>=0.5.0)
Requires-Dist: sparqlwrapper (>=1.8.5)
Requires-Dist: pyshacl (>=0.13.3)
Requires-Dist: python-dateutil (>=2.8.1)
Requires-Dist: requests
